dprunner/__init__.py
dprunner/__main__.py
dark_phoenix-0.0.3.dist-info/LICENSE
dark_phoenix-0.0.3.dist-info/METADATA
dark_phoenix-0.0.3.dist-info/WHEEL
dark_phoenix-0.0.3.dist-info/top_level.txt
dark_phoenix-0.0.3.dist-info/RECORD
