Metadata-Version: 2.1
Name: dark-phoenix
Version: 0.0.3
Summary: A test runner wrapping python unittest
Home-page: https://gitlab.com/test_framework/dark-phoenix.git
Author: atv
Author-email: andrevettickal@gmail.com
License: UNKNOWN
Platform: UNKNOWN
Classifier: Programming Language :: Python :: 3
Classifier: License :: OSI Approved :: MIT License
Classifier: Operating System :: OS Independent
